{
  "data": {
    "distrito": "Évora",
    "concelho": "Viana do Alentejo",
    "freguesia": "Alcáçovas",
    "OBJECTID": 6,
    "BGRI2021": "07130100205",
    "DT21": "07",
    "DTMN21": "0713",
    "DTMNFR21": "071301",
    "DTMNFRSEC21": "071301002",
    "SECNUM21": "002",
    "SSNUM21": "05",
    "SECSSNUM21": "00205",
    "OBJECTID_1": 63822,
    "DT": "07",
    "CC": "13",
    "fr": "01",
    "SEC": "002",
    "SS": "05"
  },
  "addresses": [
    {
      "id": "pt.ine.add.PTCONT.1389167",
      "street": "R S PEDRO",
      "house": "76",
      "postcode": "7090-041",
      "city": "ALCÁÇOVAS",
      "lon": "-8.151468848844704",
      "lat": "38.393234406396864"
    },
    {
      "id": "pt.ine.add.PTCONT.1399574",
      "street": "R S PEDRO",
      "house": "110",
      "postcode": "7090-041",
      "city": "ALCÁÇOVAS",
      "lon": "-8.150177757866443",
      "lat": "38.393142271446216"
    },
    {
      "id": "pt.ine.add.PTCONT.1417972",
      "street": "R S PEDRO",
      "house": "82",
      "postcode": "7090-041",
      "city": "ALCÁÇOVAS",
      "lon": "-8.151274257115432",
      "lat": "38.39324344540403"
    },
    {
      "id": "pt.ine.add.PTCONT.1426771",
      "street": "R S PEDRO",
      "house": "88",
      "postcode": "7090-041",
      "city": "ALCÁÇOVAS",
      "lon": "-8.151125454404122",
      "lat": "38.39326148574918"
    },
    {
      "id": "pt.ine.add.PTCONT.1426772",
      "street": "R S PEDRO",
      "house": "112",
      "postcode": "7090-041",
      "city": "ALCÁÇOVAS",
      "lon": "-8.150078067361383",
      "lat": "38.393102535075364"
    },
    {
      "id": "pt.ine.add.PTCONT.1428222",
      "street": "R S PEDRO",
      "house": "98",
      "postcode": "7090-041",
      "city": "ALCÁÇOVAS",
      "lon": "-8.150839285487685",
      "lat": "38.393256670096775"
    },
    {
      "id": "pt.ine.add.PTCONT.1431324",
      "street": "R S PEDRO",
      "house": "100",
      "postcode": "7090-041",
      "city": "ALCÁÇOVAS",
      "lon": "-8.150713366319973",
      "lat": "38.393234522293234"
    },
    {
      "id": "pt.ine.add.PTCONT.1436138",
      "street": "R ESPERANÇA",
      "house": "65",
      "postcode": "7090-029",
      "city": "ALCÁÇOVAS",
      "lon": "-8.151052518845423",
      "lat": "38.39294890620097"
    },
    {
      "id": "pt.ine.add.PTCONT.1440441",
      "street": "R S PEDRO",
      "house": "102",
      "postcode": "7090-041",
      "city": "ALCÁÇOVAS",
      "lon": "-8.150587452565432",
      "lat": "38.39323454113591"
    },
    {
      "id": "pt.ine.add.PTCONT.1442687",
      "street": "R S PEDRO",
      "house": "86",
      "postcode": "7090-041",
      "city": "ALCÁÇOVAS",
      "lon": "-8.151188317412771",
      "lat": "38.393256763624606"
    },
    {
      "id": "pt.ine.add.PTCONT.1451902",
      "street": "R S PEDRO",
      "house": "92",
      "postcode": "7090-041",
      "city": "ALCÁÇOVAS",
      "lon": "-8.151053325304995",
      "lat": "38.3932570654387"
    },
    {
      "id": "pt.ine.add.PTCONT.1463313",
      "street": "R ESPERANÇA",
      "house": "71",
      "postcode": "7090-029",
      "city": "ALCÁÇOVAS",
      "lon": "-8.150885009547133",
      "lat": "38.393000270447445"
    }
  ]
}