{"CP4":"2565","CP3":"838","Distrito":"Lisboa","Concelho":"Torres Vedras","CP":"2565-838","Artéria":" ","Localidade":"Casal Pombal","Local":"","Troço":"","Porta":"","Cliente":"","Designação Postal":"VENTOSA TVD","locais":[{"id":"pt.ine.add.PTCONT.2345981","rua":"CSL POMBAL CIMA","casa":"","coordenadas":[39.08266941067252,-9.319989250619562]},{"id":"pt.ine.add.PTCONT.2759808","rua":"CSL POMBAL DE BAIXO","casa":"","coordenadas":[39.08237565800507,-9.324063850364457]},{"id":"pt.ine.add.PTCONT.2783232","rua":"CSL POMBAL DE BAIXO","casa":"","coordenadas":[39.08304675635089,-9.322734543480447]},{"id":"pt.ine.add.PTCONT.2803244","rua":"CSL POMBAL DE BAIXO","casa":"","coordenadas":[39.08191113923501,-9.323686226530132]},{"id":"pt.ine.add.PTCONT.2815577","rua":"R SANTO ANTÓNIO","casa":"4","coordenadas":[39.08363495418221,-9.332140201561971]},{"id":"pt.ine.add.PTCONT.2822797","rua":"CHAFARIZ","casa":"7","coordenadas":[39.06393610721333,-9.357282741023134]},{"id":"pt.ine.add.PTCONT.2869270","rua":"CSL POMBAL DE BAIXO","casa":"","coordenadas":[39.08309013401983,-9.322897067841106]},{"id":"pt.ine.add.PTCONT.3099737","rua":"R SANTO ANTÓNIO","casa":"2","coordenadas":[39.08368815619119,-9.332222000801034]},{"id":"pt.ine.add.PTCONT.3145032","rua":"AV PADRE MANUEL ANTUNES","casa":"7","coordenadas":[39.06496492302795,-9.308057915035427]},{"id":"pt.ine.add.PTCONT.3384876","rua":"CSL POMBAL CIMA","casa":"","coordenadas":[39.082640629072436,-9.3201621197735]},{"id":"pt.ine.add.PTCONT.3442314","rua":"CSL POMBAL DE BAIXO","casa":"","coordenadas":[39.08255742381656,-9.323905112454566]}],"ruas":["CSL POMBAL CIMA","CSL POMBAL DE BAIXO","R SANTO ANTÓNIO","CHAFARIZ","AV PADRE MANUEL ANTUNES"],"centroide":[39.079195786797044,-9.326323591703078]}