{"CP4":"3570","CP3":"010","Distrito":"Guarda","Concelho":"Aguiar da Beira","CP":"3570-010","Artéria":"Travessa 25 de Abril","Localidade":"Aguiar da Beira","Local":"","Troço":"","Porta":"","Cliente":"","Designação Postal":"AGUIAR DA BEIRA","locais":[{"id":"pt.ine.add.PTCONT.1903225","rua":"R 25 DE ABRIL","casa":"34","coordenadas":[40.81654829625376,-7.546347307161442]},{"id":"pt.ine.add.PTCONT.1905987","rua":"R 25 DE ABRIL","casa":"4","coordenadas":[40.817596809465805,-7.5453542754543275]},{"id":"pt.ine.add.PTCONT.1910964","rua":"AV 25 ABRIL","casa":"25","coordenadas":[40.81683475040584,-7.5460129050229]},{"id":"pt.ine.add.PTCONT.1920038","rua":"R 25 DE ABRIL","casa":"8","coordenadas":[40.81727391706902,-7.545606035643276]},{"id":"pt.ine.add.PTCONT.1920741","rua":"LG DA BARREIRINHA","casa":"8","coordenadas":[40.81750150735177,-7.544323913605813]},{"id":"pt.ine.add.PTCONT.1929510","rua":"R 25 DE ABRIL","casa":"8","coordenadas":[40.816223894930644,-7.546302754771161]},{"id":"pt.ine.add.PTCONT.1945920","rua":"R 25 DE ABRIL","casa":"27","coordenadas":[40.81769543568847,-7.545270434334751]},{"id":"pt.ine.add.PTCONT.1964581","rua":"R 25 DE ABRIL","casa":"14","coordenadas":[40.81694268316745,-7.545988247835219]},{"id":"pt.ine.add.PTCONT.1966547","rua":"R 25 DE ABRIL","casa":"12","coordenadas":[40.81700535240191,-7.545916578376755]},{"id":"pt.ine.add.PTCONT.1855191","rua":"R 25 DE ABRIL","casa":"","coordenadas":[40.816134212087526,-7.546374661024358]},{"id":"pt.ine.add.PTCONT.1861234","rua":"R 25 DE ABRIL","casa":"6","coordenadas":[40.81746222576105,-7.545450286554672]},{"id":"pt.ine.add.PTCONT.1862883","rua":"R 25 DE ABRIL","casa":"17","coordenadas":[40.81607154254969,-7.546446329107805]},{"id":"pt.ine.add.PTCONT.1881989","rua":"AV 25 DE ABRIL","casa":"20","coordenadas":[40.81667315277038,-7.546109151798877]},{"id":"pt.ine.add.PTCONT.1888403","rua":"AV 25 DE ABRIL","casa":"18","coordenadas":[40.81676277512384,-7.546025392353996]}],"ruas":["R 25 DE ABRIL","AV 25 ABRIL","LG DA BARREIRINHA","AV 25 DE ABRIL"],"centroide":[40.8169202907618,-7.545807913899335]}