{
  "CP": "5180-169",
  "CP4": "5180",
  "CP3": "169",
  "Distrito": "Bragança",
  "Concelho": "Freixo de Espada à Cinta",
  "Localidade": "Freixo de Espada à Cinta",
  "Designação Postal": "FREIXO DE ESPADA À CINTA",
  "partes": [
    {
      "Artéria": "Rua da Resgalgaria",
      "Local": "",
      "Troço": "",
      "Porta": "",
      "Cliente": ""
    },
    {
      "Artéria": "Rua Doutor Virgilio Taborda",
      "Local": "",
      "Troço": "",
      "Porta": "",
      "Cliente": ""
    }
  ],
  "pontos": [
    {
      "id": "pt.ine.add.PTCONT.862668",
      "rua": "R DR VIRGÍLIO TABORDA",
      "casa": "",
      "coordenadas": [
        41.08668316351481,
        -6.811015857569991
      ]
    },
    {
      "id": "pt.ine.add.PTCONT.877503",
      "rua": "R DR VIRGÍLIO TABORDA",
      "casa": "",
      "coordenadas": [
        41.08729135524888,
        -6.811443998755746
      ]
    },
    {
      "id": "pt.ine.add.PTCONT.901412",
      "rua": "R DR VIRGÍLIO TABORDA",
      "casa": "",
      "coordenadas": [
        41.086936587588,
        -6.81112978564659
      ]
    },
    {
      "id": "pt.ine.add.PTCONT.901413",
      "rua": "R DR VIRGÍLIO TABORDA",
      "casa": "",
      "coordenadas": [
        41.08617713438498,
        -6.810859391808103
      ]
    },
    {
      "id": "pt.ine.add.PTCONT.901414",
      "rua": "R DR VIRGÍLIO TABORDA",
      "casa": "",
      "coordenadas": [
        41.08617713438498,
        -6.810859391808103
      ]
    },
    {
      "id": "pt.ine.add.PTCONT.901477",
      "rua": "R DR VIRGÍLIO TABORDA",
      "casa": "",
      "coordenadas": [
        41.08617713438498,
        -6.810859391808103
      ]
    },
    {
      "id": "pt.ine.add.PTCONT.901560",
      "rua": "R DR VIRGÍLIO TABORDA",
      "casa": "",
      "coordenadas": [
        41.08617713438498,
        -6.810859391808103
      ]
    },
    {
      "id": "pt.ine.add.PTCONT.903028",
      "rua": "R DR VIRGÍLIO TABORDA",
      "casa": "",
      "coordenadas": [
        41.08710552718845,
        -6.811147658908493
      ]
    },
    {
      "id": "pt.ine.add.PTCONT.903311",
      "rua": "R DR VIRGÍLIO TABORDA",
      "casa": "43",
      "coordenadas": [
        41.08545478153878,
        -6.810683464652429
      ]
    },
    {
      "id": "pt.ine.add.PTCONT.910665",
      "rua": "R DR VIRGÍLIO TABORDA",
      "casa": "28",
      "coordenadas": [
        41.08632634602626,
        -6.8105231796326935
      ]
    },
    {
      "id": "pt.ine.add.PTCONT.910666",
      "rua": "R DR VIRGÍLIO TABORDA",
      "casa": "28",
      "coordenadas": [
        41.08632634602626,
        -6.8105231796326935
      ]
    },
    {
      "id": "pt.ine.add.PTCONT.910667",
      "rua": "R DR VIRGÍLIO TABORDA",
      "casa": "28",
      "coordenadas": [
        41.08632634602626,
        -6.8105231796326935
      ]
    },
    {
      "id": "pt.ine.add.PTCONT.910668",
      "rua": "R DR VIRGÍLIO TABORDA",
      "casa": "28",
      "coordenadas": [
        41.08632634602626,
        -6.8105231796326935
      ]
    },
    {
      "id": "pt.ine.add.PTCONT.914701",
      "rua": "R DR VIRGÍLIO TABORDA",
      "casa": "",
      "coordenadas": [
        41.08682241741834,
        -6.810596537022673
      ]
    },
    {
      "id": "pt.ine.add.PTCONT.917998",
      "rua": "R DR VIRGÍLIO TABORDA",
      "casa": "",
      "coordenadas": [
        41.08723869901838,
        -6.810778603521009
      ]
    },
    {
      "id": "pt.ine.add.PTCONT.920327",
      "rua": "R DR VIRGÍLIO TABORDA",
      "casa": "",
      "coordenadas": [
        41.08742025079916,
        -6.811691335209017
      ]
    },
    {
      "id": "pt.ine.add.PTCONT.923046",
      "rua": "R DR VIRGÍLIO TABORDA",
      "casa": "",
      "coordenadas": [
        41.0859872792145,
        -6.811577238742644
      ]
    },
    {
      "id": "pt.ine.add.PTCONT.926122",
      "rua": "R DR VIRGÍLIO TABORDA",
      "casa": "",
      "coordenadas": [
        41.085630862418974,
        -6.810334816301625
      ]
    },
    {
      "id": "pt.ine.add.PTCONT.929233",
      "rua": "R DR VIRGÍLIO TABORDA",
      "casa": "",
      "coordenadas": [
        41.08644828971912,
        -6.810949161476243
      ]
    },
    {
      "id": "pt.ine.add.PTCONT.929234",
      "rua": "R DR VIRGÍLIO TABORDA",
      "casa": "",
      "coordenadas": [
        41.08644828971912,
        -6.810949161476243
      ]
    },
    {
      "id": "pt.ine.add.PTCONT.929626",
      "rua": "R DR VIRGÍLIO TABORDA",
      "casa": "",
      "coordenadas": [
        41.08644828971912,
        -6.810949161476243
      ]
    },
    {
      "id": "pt.ine.add.PTCONT.929764",
      "rua": "R DR VIRGÍLIO TABORDA",
      "casa": "",
      "coordenadas": [
        41.08644828971912,
        -6.810949161476243
      ]
    },
    {
      "id": "pt.ine.add.PTCONT.937324",
      "rua": "R DR VIRGÍLIO TABORDA",
      "casa": "",
      "coordenadas": [
        41.087216499261004,
        -6.811289950620527
      ]
    },
    {
      "id": "pt.ine.add.PTCONT.941247",
      "rua": "R DR VIRGÍLIO TABORDA",
      "casa": "",
      "coordenadas": [
        41.08590160834242,
        -6.8103888893561635
      ]
    },
    {
      "id": "pt.ine.add.PTCONT.941379",
      "rua": "R DR VIRGÍLIO TABORDA",
      "casa": "",
      "coordenadas": [
        41.085504286627064,
        -6.81028975260442
      ]
    },
    {
      "id": "pt.ine.add.PTCONT.948082",
      "rua": "R DR VIRGÍLIO TABORDA",
      "casa": "1",
      "coordenadas": [
        41.08563564290867,
        -6.8107512418471305
      ]
    }
  ],
  "ruas": [
    "R DR VIRGÍLIO TABORDA"
  ],
  "centro": [
    41.08643751616897,
    -6.810990543906718
  ],
  "poligono": [
    [
      41.08575431148137,
      -6.811186212578175
    ],
    [
      41.08568774927191,
      -6.811074490816898
    ],
    [
      41.08563028085563,
      -6.81097058252503
    ],
    [
      41.08558190623254,
      -6.810874487702573
    ],
    [
      41.08554262540264,
      -6.810786206349524
    ],
    [
      41.085512438365924,
      -6.8107057384658845
    ],
    [
      41.0854913451224,
      -6.810633084051655
    ],
    [
      41.085479345672056,
      -6.810568243106836
    ],
    [
      41.0854764400149,
      -6.810511215631425
    ],
    [
      41.08548262815094,
      -6.810462001625424
    ],
    [
      41.08550863856358,
      -6.810423732876708
    ],
    [
      41.085554471252834,
      -6.810396409385278
    ],
    [
      41.0856201262187,
      -6.810380031151133
    ],
    [
      41.08570560346117,
      -6.810374598174272
    ],
    [
      41.085810902980256,
      -6.810380110454698
    ],
    [
      41.08593602477595,
      -6.8103965679924094
    ],
    [
      41.08608096884825,
      -6.810423970787406
    ],
    [
      41.08624573519715,
      -6.810462318839687
    ],
    [
      41.08639641015245,
      -6.81049871817447
    ],
    [
      41.08653299371414,
      -6.810533168791753
    ],
    [
      41.086655485882204,
      -6.81056567069154
    ],
    [
      41.086763886656655,
      -6.8105962238738265
    ],
    [
      41.086858196037504,
      -6.810624828338614
    ],
    [
      41.086938414024736,
      -6.810651484085906
    ],
    [
      41.08700454061835,
      -6.810676191115696
    ],
    [
      41.087056575818366,
      -6.810698949427987
    ],
    [
      41.08710494336495,
      -6.810733124383868
    ],
    [
      41.0871496432581,
      -6.810778715983337
    ],
    [
      41.08719067549782,
      -6.810835724226395
    ],
    [
      41.08722804008413,
      -6.810904149113041
    ],
    [
      41.087261737017,
      -6.810983990643277
    ],
    [
      41.087291766296445,
      -6.811075248817101
    ],
    [
      41.08731812792247,
      -6.811177923634513
    ],
    [
      41.08734082189507,
      -6.811292015095514
    ],
    [
      41.08733828894008,
      -6.811390062366602
    ],
    [
      41.087310529057504,
      -6.811472065447778
    ],
    [
      41.08725754224735,
      -6.811538024339042
    ],
    [
      41.087179328509606,
      -6.811587939040395
    ],
    [
      41.08707588784428,
      -6.811621809551834
    ],
    [
      41.08694722025137,
      -6.811639635873363
    ],
    [
      41.08679332573087,
      -6.811641418004979
    ],
    [
      41.08661420428279,
      -6.811627155946683
    ],
    [
      41.08644915273953,
      -6.8116007114255135
    ],
    [
      41.086298171101106,
      -6.811562084441471
    ],
    [
      41.08616125936751,
      -6.811511274994556
    ],
    [
      41.08603841753873,
      -6.81144828308477
    ],
    [
      41.08592964561478,
      -6.811373108712111
    ],
    [
      41.085834943595664,
      -6.811285751876579
    ],
    [
      41.08575431148137,
      -6.811186212578175
    ]
  ],
  "centroide": [
    41.0864046191027,
    -6.8109361552920324
  ],
  "centroDeMassa": [
    41.08643751616897,
    -6.810990543906718
  ]
}