{"CP4":"7400","CP3":"230","Distrito":"Portalegre","Concelho":"Ponte de Sor","CP":"7400-230","Artéria":"Largo Marquês de Pombal","Localidade":"Ponte de Sor","Local":"","Troço":"","Porta":"","Cliente":"","Designação Postal":"PONTE DE SOR","locais":[{"id":"pt.ine.add.PTCONT.3535313","rua":"LG MQ DE POMBAL","casa":"9","coordenadas":[39.24778864299172,-8.009086429452708]},{"id":"pt.ine.add.PTCONT.3483075","rua":"LG MQ DE POMBAL","casa":"13","coordenadas":[39.24780717475904,-8.009572938910896]},{"id":"pt.ine.add.PTCONT.3483076","rua":"LG MQ DE POMBAL","casa":"13","coordenadas":[39.24780717475904,-8.009572938910896]},{"id":"pt.ine.add.PTCONT.3483077","rua":"LG MQ DE POMBAL","casa":"13","coordenadas":[39.24780717475904,-8.009572938910896]},{"id":"pt.ine.add.PTCONT.3483078","rua":"LG MQ DE POMBAL","casa":"13","coordenadas":[39.24780717475904,-8.009572938910896]},{"id":"pt.ine.add.PTCONT.3504935","rua":"LG MQ DE POMBAL","casa":"6","coordenadas":[39.24776183048461,-8.009283410256561]},{"id":"pt.ine.add.PTCONT.3504936","rua":"LG MQ DE POMBAL","casa":"6","coordenadas":[39.24776183048461,-8.009283410256561]},{"id":"pt.ine.add.PTCONT.3505250","rua":"LG MQ DE POMBAL","casa":"6","coordenadas":[39.24776183048461,-8.009283410256561]},{"id":"pt.ine.add.PTCONT.3507256","rua":"LG MQ DE POMBAL","casa":"7","coordenadas":[39.24780655896643,-8.00899372321316]}],"ruas":["LG MQ DE POMBAL"],"centroide":[39.24778785418521,-8.009403551983246]}