{"CP4":"3260","CP3":"426","Distrito":"Leiria","Concelho":"Figueiró dos Vinhos","CP":"3260-426","Artéria":"Rua Jose Simões de Abreu","Localidade":"Figueiró dos Vinhos","Local":"","Troço":"","Porta":"","Cliente":"","Designação Postal":"FIGUEIRÓ DOS VINHOS","locais":[{"id":"pt.ine.add.PTCONT.1990544","rua":"R MADRE DEUS","casa":"","coordenadas":[39.90433490260349,-8.279776226302292]},{"id":"pt.ine.add.PTCONT.1993823","rua":"R MADRE DE DEUS","casa":"4","coordenadas":[39.903165098723406,-8.278966850515364]},{"id":"pt.ine.add.PTCONT.2129321","rua":"R MADRE DE DEUS","casa":"14","coordenadas":[39.9031107074721,-8.279247389421368]},{"id":"pt.ine.add.PTCONT.2132818","rua":"QTA CERCA DAS FREIRAS","casa":"","coordenadas":[39.90273235355568,-8.279316748806778]},{"id":"pt.ine.add.PTCONT.2155619","rua":"R MADRE DE DEUS","casa":"12","coordenadas":[39.90314683587859,-8.279165608646142]},{"id":"pt.ine.add.PTCONT.2253780","rua":"R MADRE DE DEUS","casa":"","coordenadas":[39.90589262536536,-8.280071907845553]},{"id":"pt.ine.add.PTCONT.2255870","rua":"R MADRE DE DEUS","casa":"8","coordenadas":[39.903191955827694,-8.279095540806114]},{"id":"pt.ine.add.PTCONT.2268380","rua":"R MADRE DE DEUS","casa":"","coordenadas":[39.90284088587695,-8.278954469186194]}],"ruas":["R MADRE DEUS","R MADRE DE DEUS","QTA CERCA DAS FREIRAS"],"centroide":[39.90365349706091,-8.27937718176337]}337]}}