{
  "data": {
    "distrito": "Porto",
    "concelho": "Lousada",
    "freguesia": "União das freguesias de Silvares, Pias, Nogueira e Alvarenga",
    "OBJECTID": 178,
    "BGRI2021": "13053200222",
    "DT21": "13",
    "DTMN21": "1305",
    "DTMNFR21": "130532",
    "DTMNFRSEC21": "130532002",
    "SECNUM21": "002",
    "SSNUM21": "22",
    "SECSSNUM21": "00222",
    "OBJECTID_1": 130065,
    "DT": "13",
    "CC": "05",
    "fr": "32",
    "SEC": "002",
    "SS": "22"
  },
  "addresses": [
    {
      "id": "pt.ine.add.PTCONT.3581172",
      "street": "ESTR BOAVISTA",
      "house": "517",
      "postcode": "4620-638",
      "city": "LOUSADA",
      "lon": "-8.274440280302475",
      "lat": "41.277384275346215"
    },
    {
      "id": "pt.ine.add.PTCONT.3581173",
      "street": "R CARVALHO",
      "house": "",
      "postcode": "4620-647",
      "city": "LOUSADA",
      "lon": "-8.273267126293385",
      "lat": "41.27577395801007"
    },
    {
      "id": "pt.ine.add.PTCONT.3592058",
      "street": "R CARVALHO",
      "house": "263",
      "postcode": "4620-647",
      "city": "LOUSADA",
      "lon": "-8.273828287421185",
      "lat": "41.27586331547379"
    },
    {
      "id": "pt.ine.add.PTCONT.3614921",
      "street": "R BOAVISTA",
      "house": "107",
      "postcode": "4620-638",
      "city": "LOUSADA",
      "lon": "-8.273745125451399",
      "lat": "41.27604350108168"
    },
    {
      "id": "pt.ine.add.PTCONT.3693137",
      "street": "R BOAVISTA",
      "house": "135",
      "postcode": "4620-638",
      "city": "LOUSADA",
      "lon": "-8.274032101128952",
      "lat": "41.276286263540804"
    },
    {
      "id": "pt.ine.add.PTCONT.3719135",
      "street": "R BOAVISTA",
      "house": "113",
      "postcode": "4620-638",
      "city": "LOUSADA",
      "lon": "-8.273840706414791",
      "lat": "41.27608840527994"
    },
    {
      "id": "pt.ine.add.PTCONT.3741896",
      "street": "R CARVALHO",
      "house": "279",
      "postcode": "4620-647",
      "city": "LOUSADA",
      "lon": "-8.273625268055993",
      "lat": "41.27580953824506"
    },
    {
      "id": "pt.ine.add.PTCONT.3863957",
      "street": "ESTR BOAVISTA",
      "house": "541",
      "postcode": "4620-638",
      "city": "LOUSADA",
      "lon": "-8.274762487874895",
      "lat": "41.27735686675738"
    },
    {
      "id": "pt.ine.add.PTCONT.3910669",
      "street": "R BOAVISTA",
      "house": "15",
      "postcode": "4620-638",
      "city": "LOUSADA",
      "lon": "-8.272647535769295",
      "lat": "41.2762699416107"
    },
    {
      "id": "pt.ine.add.PTCONT.3935040",
      "street": "ESTR BOAVISTA",
      "house": "487",
      "postcode": "4620-638",
      "city": "LOUSADA",
      "lon": "-8.274106136675856",
      "lat": "41.277411697652106"
    },
    {
      "id": "pt.ine.add.PTCONT.3947912",
      "street": "ESTR BOAVISTA",
      "house": "451",
      "postcode": "4620-638",
      "city": "LOUSADA",
      "lon": "-8.273795612992338",
      "lat": "41.27732203556234"
    },
    {
      "id": "pt.ine.add.PTCONT.3987130",
      "street": "ESTR BOAVISTA",
      "house": "537",
      "postcode": "4620-638",
      "city": "LOUSADA",
      "lon": "-8.27453576651785",
      "lat": "41.27738415808649"
    },
    {
      "id": "pt.ine.add.PTCONT.4031603",
      "street": "ESTR BOAVISTA",
      "house": "441",
      "postcode": "4620-638",
      "city": "LOUSADA",
      "lon": "-8.273664068453328",
      "lat": "41.27720514166958"
    },
    {
      "id": "pt.ine.add.PTCONT.4052455",
      "street": "ESTR BOAVISTA",
      "house": "529",
      "postcode": "4620-638",
      "city": "LOUSADA",
      "lon": "-8.274428169732504",
      "lat": "41.277303252437164"
    },
    {
      "id": "pt.ine.add.PTCONT.4064738",
      "street": "ESTR BOAVISTA",
      "house": "509",
      "postcode": "4620-638",
      "city": "LOUSADA",
      "lon": "-8.274213616890618",
      "lat": "41.27743857856122"
    },
    {
      "id": "pt.ine.add.PTCONT.4071260",
      "street": "R BOAVISTA",
      "house": "67",
      "postcode": "4620-638",
      "city": "LOUSADA",
      "lon": "-8.273267569294333",
      "lat": "41.27598105406248"
    },
    {
      "id": "pt.ine.add.PTCONT.4077485",
      "street": "R CARVALHO",
      "house": "345",
      "postcode": "4620-647",
      "city": "LOUSADA",
      "lon": "-8.273136066880356",
      "lat": "41.275882167885776"
    },
    {
      "id": "pt.ine.add.PTCONT.4090711",
      "street": "R BOAVISTA",
      "house": "131",
      "postcode": "4620-638",
      "city": "LOUSADA",
      "lon": "-8.273972268378754",
      "lat": "41.276214303172104"
    },
    {
      "id": "pt.ine.add.PTCONT.4103833",
      "street": "R BOAVISTA",
      "house": "153",
      "postcode": "4620-638",
      "city": "LOUSADA",
      "lon": "-8.27408015340408",
      "lat": "41.27643027189335"
    },
    {
      "id": "pt.ine.add.PTCONT.4140739",
      "street": "ESTR BOAVISTA",
      "house": "427",
      "postcode": "4620-638",
      "city": "LOUSADA",
      "lon": "-8.273556453735239",
      "lat": "41.27711523102674"
    },
    {
      "id": "pt.ine.add.PTCONT.4162840",
      "street": "R BOAVISTA",
      "house": "",
      "postcode": "4620-638",
      "city": "LOUSADA",
      "lon": "-8.274092263379407",
      "lat": "41.276511294852284"
    },
    {
      "id": "pt.ine.add.PTCONT.4175733",
      "street": "R BOAVISTA",
      "house": "203",
      "postcode": "4620-638",
      "city": "LOUSADA",
      "lon": "-8.273687263761753",
      "lat": "41.27688996642637"
    },
    {
      "id": "pt.ine.add.PTCONT.4182294",
      "street": "ESTR BOAVISTA",
      "house": "471",
      "postcode": "4620-638",
      "city": "LOUSADA",
      "lon": "-8.273915048055027",
      "lat": "41.27735790633841"
    },
    {
      "id": "pt.ine.add.PTCONT.4221698",
      "street": "R BOAVISTA",
      "house": "197",
      "postcode": "4620-638",
      "city": "LOUSADA",
      "lon": "-8.273782633265435",
      "lat": "41.27683582474564"
    },
    {
      "id": "pt.ine.add.PTCONT.4241393",
      "street": "ESTR BOAVISTA",
      "house": "401",
      "postcode": "4620-638",
      "city": "LOUSADA",
      "lon": "-8.273448820025937",
      "lat": "41.277016316107115"
    },
    {
      "id": "pt.ine.add.PTCONT.4250858",
      "street": "R BOAVISTA",
      "house": "175",
      "postcode": "4620-638",
      "city": "LOUSADA",
      "lon": "-8.273997107582435",
      "lat": "41.27666448271369"
    },
    {
      "id": "pt.ine.add.PTCONT.4287731",
      "street": "R BOAVISTA",
      "house": "179",
      "postcode": "4620-638",
      "city": "LOUSADA",
      "lon": "-8.273925648521312",
      "lat": "41.276736603726775"
    },
    {
      "id": "pt.ine.add.PTCONT.4343785",
      "street": "R BOAVISTA",
      "house": "85",
      "postcode": "4620-638",
      "city": "LOUSADA",
      "lon": "-8.273446640693665",
      "lat": "41.27599884431711"
    },
    {
      "id": "pt.ine.add.PTCONT.4360018",
      "street": "ESTR BOAVISTA",
      "house": "273",
      "postcode": "4620-638",
      "city": "LOUSADA",
      "lon": "-8.272313186628985",
      "lat": "41.276198312775165"
    },
    {
      "id": "pt.ine.add.PTCONT.4360021",
      "street": "ESTR BOAVISTA",
      "house": "273",
      "postcode": "4620-638",
      "city": "LOUSADA",
      "lon": "-8.272313186628985",
      "lat": "41.276198312775165"
    },
    {
      "id": "pt.ine.add.PTCONT.4377038",
      "street": "R BOAVISTA",
      "house": "21",
      "postcode": "4620-638",
      "city": "LOUSADA",
      "lon": "-8.272742905233468",
      "lat": "41.27621580078548"
    },
    {
      "id": "pt.ine.add.PTCONT.4381055",
      "street": "R CARVALHO",
      "house": "247",
      "postcode": "4620-647",
      "city": "LOUSADA",
      "lon": "-8.273959597278928",
      "lat": "41.27587215909992"
    },
    {
      "id": "pt.ine.add.PTCONT.4387764",
      "street": "R BOAVISTA",
      "house": "89",
      "postcode": "4620-638",
      "city": "LOUSADA",
      "lon": "-8.273566015246136",
      "lat": "41.27600770294005"
    }
  ]
}